booking_scraper/__init__.py
booking_scraper/bkscraper.py
booking_scraper/core/ThreadScraper.py
booking_scraper/core/__init__.py
booking_scraper/core/core.py
booking_scraper-1.0.1.dist-info/LICENSE
booking_scraper-1.0.1.dist-info/METADATA
booking_scraper-1.0.1.dist-info/WHEEL
booking_scraper-1.0.1.dist-info/top_level.txt
booking_scraper-1.0.1.dist-info/RECORD
