Metadata-Version: 2.1
Name: booking_scraper
Version: 1.0.1
Summary: A scraper for the booking.com website
Home-page: https://github.com/HexNio/booking_scraper
Author: HexNio
Author-email: 
License: UNKNOWN
Keywords: scarper,web scraperbeautifulsoup4automation
Platform: UNKNOWN
Classifier: Programming Language :: Python :: 3 :: Only
Classifier: License :: OSI Approved :: GNU General Public License v3 (GPLv3)
Classifier: Operating System :: MacOS :: MacOS X
Classifier: Intended Audience :: Other Audience
Classifier: Intended Audience :: Education
Classifier: Topic :: Internet
Requires-Python: >=3.6
